read_only_class_attributes/__init__.py
read_only_class_attributes/_version.py
read_only_class_attributes/read_only_decorator.py
read_only_class_attributes-1.0.1.dist-info/METADATA
read_only_class_attributes-1.0.1.dist-info/WHEEL
read_only_class_attributes-1.0.1.dist-info/top_level.txt
read_only_class_attributes-1.0.1.dist-info/RECORD
