Metadata-Version: 2.1
Name: read-only-class-attributes
Version: 1.0.1
Summary: This package provides a decorator to make read only attributes on a given Python class
Home-page: https://github.com/pavanchhatpar/python-read-only-class-attributes
Author: Pavan Chhatpar
Author-email: pavanchhatpar@gmail.com
License: MIT
Platform: UNKNOWN
